pgcopy/__init__.py
pgcopy/copy.py
pgcopy/inspect.py
pgcopy/thread.py
pgcopy/util.py
pgcopy/version.py
pgcopy/contrib/__init__.py
pgcopy/contrib/vector.py
pgcopy/errors/__init__.py
pgcopy/errors/py2.py
pgcopy/errors/py3.py
pgcopy-1.6.1.dist-info/licenses/AUTHORS.rst
pgcopy-1.6.1.dist-info/licenses/LICENSE.txt
pgcopy-1.6.1.dist-info/METADATA
pgcopy-1.6.1.dist-info/WHEEL
pgcopy-1.6.1.dist-info/top_level.txt
pgcopy-1.6.1.dist-info/RECORD
