Metadata-Version: 2.4
Name: pgcopy
Version: 1.6.1
Summary: Fast db insert with postgresql binary copy
Home-page: https://pgcopy.readthedocs.io/en/latest/
Author: Aryeh Leib Taurog
Author-email: python@aryehleib.com
License: MIT
Classifier: Programming Language :: Python :: 3
Classifier: Programming Language :: Python :: 3.8
Classifier: Programming Language :: Python :: 3.9
Classifier: Programming Language :: Python :: 3.10
Classifier: Programming Language :: Python :: 3.11
Classifier: Programming Language :: Python :: 3.12
Classifier: Development Status :: 5 - Production/Stable
Classifier: License :: OSI Approved :: MIT License
Classifier: Operating System :: OS Independent
Classifier: Intended Audience :: Developers
Classifier: Topic :: Database
License-File: LICENSE.txt
License-File: AUTHORS.rst
Requires-Dist: psycopg2
Requires-Dist: pytz
Dynamic: author
Dynamic: author-email
Dynamic: classifier
Dynamic: description
Dynamic: description-content-type
Dynamic: home-page
Dynamic: license
Dynamic: license-file
Dynamic: requires-dist
Dynamic: summary
